remodeler/__init__.py
remodeler/backup_manager.py
remodeler/dispatcher.py
remodeler/remodeler_validator.py
remodeler/cli/__init__.py
remodeler/cli/run_remodel.py
remodeler/cli/run_remodel_backup.py
remodeler/cli/run_remodel_restore.py
remodeler/operations/__init__.py
remodeler/operations/base_op.py
remodeler/operations/base_summary.py
remodeler/operations/convert_columns_op.py
remodeler/operations/factor_column_op.py
remodeler/operations/factor_hed_tags_op.py
remodeler/operations/factor_hed_type_op.py
remodeler/operations/merge_consecutive_op.py
remodeler/operations/number_groups_op.py
remodeler/operations/number_rows_op.py
remodeler/operations/remap_columns_op.py
remodeler/operations/remove_columns_op.py
remodeler/operations/remove_rows_op.py
remodeler/operations/rename_columns_op.py
remodeler/operations/reorder_columns_op.py
remodeler/operations/split_rows_op.py
remodeler/operations/summarize_column_names_op.py
remodeler/operations/summarize_column_values_op.py
remodeler/operations/summarize_definitions_op.py
remodeler/operations/summarize_hed_tags_op.py
remodeler/operations/summarize_hed_type_op.py
remodeler/operations/summarize_hed_validation_op.py
remodeler/operations/summarize_sidecar_from_events_op.py
remodeler/operations/valid_operations.py
table_remodeler-0.2.0.dist-info/licenses/LICENSE
table_remodeler-0.2.0.dist-info/METADATA
table_remodeler-0.2.0.dist-info/WHEEL
table_remodeler-0.2.0.dist-info/entry_points.txt
table_remodeler-0.2.0.dist-info/top_level.txt
table_remodeler-0.2.0.dist-info/RECORD
