Metadata-Version: 2.4
Name: table-remodeler
Version: 0.2.0
Summary: Tabular file remodeling and reorganizing tools for event files and datasets.
Author-email: Monique Dennisen <moniquedenissen.95@gmail.com>, Kay Robbins <Kay.Robbins@utsa.edu>
Maintainer-email: Monique Dennisen <moniquedenissen.95@gmail.com>, Kay Robbins <Kay.Robbins@utsa.edu>
License: MIT
Project-URL: Homepage, https://www.hedtags.org/table-remodeler/
Project-URL: Documentation, https://www.hedtags.org/table-remodeler/
Project-URL: Repository, https://github.com/hed-standard/table-remodeler
Project-URL: Bug Tracker, https://github.com/hed-standard/table-remodeler/issues
Project-URL: Changelog, https://github.com/hed-standard/table-remodeler/blob/main/CHANGELOG.md
Project-URL: HED Resources, https://www.hedtags.org/hed-resources
Keywords: remodeling,tabular data,event files,neuroscience,BIDS,HED,data transformation
Classifier: Programming Language :: Python :: 3
Classifier: Programming Language :: Python :: 3.10
Classifier: Programming Language :: Python :: 3.11
Classifier: Programming Language :: Python :: 3.12
Classifier: Programming Language :: Python :: 3.13
Classifier: Programming Language :: Python :: 3.14
Classifier: Operating System :: OS Independent
Classifier: Development Status :: 4 - Beta
Classifier: Intended Audience :: Developers
Classifier: Intended Audience :: Science/Research
Classifier: Topic :: Scientific/Engineering
Classifier: Topic :: Software Development :: Libraries :: Python Modules
Classifier: License :: OSI Approved :: MIT License
Requires-Python: >=3.10
License-File: LICENSE
Requires-Dist: hedtools>=0.8.1
Requires-Dist: jsonschema>=4.23.0
Requires-Dist: numpy>=2.0.2
Requires-Dist: openpyxl>=3.1.5
Requires-Dist: pandas>=2.2.3
Requires-Dist: semantic-version>=2.10.0
Provides-Extra: dev
Requires-Dist: ruff>=0.8.0; extra == "dev"
Requires-Dist: codespell>=2.2.0; extra == "dev"
Requires-Dist: black>=24.0.0; extra == "dev"
Requires-Dist: linkchecker>=10.0.0; extra == "dev"
Requires-Dist: mdformat>=0.7.0; extra == "dev"
Requires-Dist: mdformat-myst>=0.1.5; extra == "dev"
Requires-Dist: mdformat-tables>=0.4.0; extra == "dev"
Requires-Dist: jupyter>=1.0.0; extra == "dev"
Requires-Dist: notebook>=7.0.0; extra == "dev"
Requires-Dist: nbconvert>=7.0.0; extra == "dev"
Provides-Extra: docs
Requires-Dist: sphinx>=7.0.0; extra == "docs"
Requires-Dist: furo>=2023.9.10; extra == "docs"
Requires-Dist: sphinx-copybutton>=0.5.2; extra == "docs"
Requires-Dist: myst-parser>=2.0.0; extra == "docs"
Requires-Dist: sphinx-autodoc-typehints>=1.24.0; extra == "docs"
Requires-Dist: linkify-it-py>=2.0.0; extra == "docs"
Provides-Extra: test
Requires-Dist: coverage>=7.0.0; extra == "test"
Requires-Dist: nbconvert>=7.0.0; extra == "test"
Requires-Dist: ipykernel>=6.0.0; extra == "test"
Dynamic: license-file
